mggp.py
mggp-0.0.2.dist-info/LICENSE.txt
mggp-0.0.2.dist-info/METADATA
mggp-0.0.2.dist-info/WHEEL
mggp-0.0.2.dist-info/top_level.txt
mggp-0.0.2.dist-info/RECORD
