Metadata-Version: 2.1
Name: mggp
Version: 0.0.2
Summary: Multi Gene Genetic Programming toolbox for System Identification
Home-page: UNKNOWN
Author: Henrique Castro
Author-email: henriquec.castro@outlook.com
License: UNKNOWN
Platform: UNKNOWN
Classifier: Programming Language :: Python :: 3
Classifier: License :: OSI Approved :: MIT License
Classifier: Operating System :: OS Independent
Requires-Python: >=3.6
Requires-Dist: deap
